rf_django_envconfig/.__init__.py.swp
rf_django_envconfig/__init__.py
rf_django_envconfig-0.1.0.dist-info/DESCRIPTION.rst
rf_django_envconfig-0.1.0.dist-info/METADATA
rf_django_envconfig-0.1.0.dist-info/RECORD
rf_django_envconfig-0.1.0.dist-info/WHEEL
rf_django_envconfig-0.1.0.dist-info/metadata.json
rf_django_envconfig-0.1.0.dist-info/top_level.txt
