Metadata-Version: 2.0
Name: rf-django-envconfig
Version: 0.1.0
Summary: Helpers to configure Django settings by environment variables
Home-page: https://github.com/rfleschenberg/rf-django-envconfig
Author: René Fleschenberg
Author-email: rene@fleschenberg.net
License: BSD
Platform: UNKNOWN
Classifier: Development Status :: 5 - Production/Stable
Classifier: Intended Audience :: Developers
Classifier: License :: OSI Approved :: BSD License
Classifier: Operating System :: Unix
Classifier: Operating System :: POSIX
Classifier: Operating System :: Microsoft :: Windows
Classifier: Programming Language :: Python
Classifier: Programming Language :: Python :: 2.7
Classifier: Programming Language :: Python :: 3
Classifier: Programming Language :: Python :: 3.5
Classifier: Programming Language :: Python :: Implementation :: CPython
Classifier: Programming Language :: Python :: Implementation :: PyPy
Classifier: Topic :: Utilities
Requires-Dist: dj-database-url (>=0.4.1)
